voxfactory_mcp/__init__.py
voxfactory_mcp/serve.py
voxfactory_mcp-0.3.0.dist-info/METADATA
voxfactory_mcp-0.3.0.dist-info/WHEEL
voxfactory_mcp-0.3.0.dist-info/entry_points.txt
voxfactory_mcp-0.3.0.dist-info/top_level.txt
voxfactory_mcp-0.3.0.dist-info/RECORD
