Metadata-Version: 2.4
Name: voxfactory_mcp
Version: 0.3.0
Summary: Add your description here
Requires-Python: >=3.12
Requires-Dist: httpx>=0.28.1
Requires-Dist: mcp[cli]>=1.6.0
